setup.py
nidmviewer/__init__.py
nidmviewer/browser.py
nidmviewer/convert.py
nidmviewer/scripts.py
nidmviewer/sparql.py
nidmviewer/templates.py
nidmviewer/utils.py
nidmviewer/viewer.py
nidmviewer.egg-info/PKG-INFO
nidmviewer.egg-info/SOURCES.txt
nidmviewer.egg-info/dependency_links.txt
nidmviewer.egg-info/entry_points.txt
nidmviewer.egg-info/pbr.json
nidmviewer.egg-info/requires.txt
nidmviewer.egg-info/top_level.txt
nidmviewer/data/MNI152_T1_2mm_brain.nii.gz
nidmviewer/data/__init__.py
nidmviewer/template/__init__.py
nidmviewer/template/embed.html
nidmviewer/template/index.html