Metadata-Version: 1.0
Name: nidmviewer
Version: 0.1.3
Summary: command line or server tool to view or compare nidm results.
Home-page: http://www.github.com/vsoch/nidmviewer
Author: Vanessa Sochat
Author-email: vsochat@stanford.edu
License: LICENSE.txt
Keywords: nidm nidm-results brain imaging neuroimaging
Platform: UNKNOWN
